sagemaker_ssh_helper/VERSION
sagemaker_ssh_helper/__init__.py
sagemaker_ssh_helper/aws.py
sagemaker_ssh_helper/browser_automation.py
sagemaker_ssh_helper/deregister_old_instances_from_ssm.py
sagemaker_ssh_helper/detached_sagemaker.py
sagemaker_ssh_helper/env.py
sagemaker_ssh_helper/ide.py
sagemaker_ssh_helper/interactive_sagemaker.py
sagemaker_ssh_helper/log.py
sagemaker_ssh_helper/manager.py
sagemaker_ssh_helper/proxy.py
sagemaker_ssh_helper/sm-connect-ssh-proxy
sagemaker_ssh_helper/sm-helper-functions
sagemaker_ssh_helper/sm-init-ssm
sagemaker_ssh_helper/sm-local-configure
sagemaker_ssh_helper/sm-local-ssh-ide
sagemaker_ssh_helper/sm-local-ssh-inference
sagemaker_ssh_helper/sm-local-ssh-notebook
sagemaker_ssh_helper/sm-local-ssh-processing
sagemaker_ssh_helper/sm-local-ssh-training
sagemaker_ssh_helper/sm-local-ssh-transform
sagemaker_ssh_helper/sm-local-start-ssh
sagemaker_ssh_helper/sm-save-env
sagemaker_ssh_helper/sm-setup-ssh
sagemaker_ssh_helper/sm-ssh-ide
sagemaker_ssh_helper/sm-wait
sagemaker_ssh_helper/sm_ssh.py
sagemaker_ssh_helper/wrapper.py
sagemaker_ssh_helper/cdk/__init__.py
sagemaker_ssh_helper/cdk/advanced_tier_app.py
sagemaker_ssh_helper/cdk/iam_ssm_app.py
sagemaker_ssh_helper/cdk/low_gpu_lambda_app.py
sagemaker_ssh_helper/cdk/tests_app.py
sagemaker_ssh_helper/cdk/iam_ssm/__init__.py
sagemaker_ssh_helper/cdk/iam_ssm/advanced_tier_lambda.py
sagemaker_ssh_helper/cdk/iam_ssm/iam_ssm_stack.py
sagemaker_ssh_helper/cdk/iam_ssm/iam_ssm_stack_tests.py
sagemaker_ssh_helper/cdk/iam_ssm/ssm_advanced_tier_stack.py
sagemaker_ssh_helper/cdk/iam_ssm/trust_relationship_lambda.py
sagemaker_ssh_helper/cdk/low_gpu/__init__.py
sagemaker_ssh_helper/cdk/low_gpu/low_gpu_lambda.py
sagemaker_ssh_helper/cdk/low_gpu/low_gpu_lambda_stack.py
sagemaker_ssh_helper/cdk/tests/__init__.py
sagemaker_ssh_helper/cdk/tests/unit/__init__.py
sagemaker_ssh_helper/js/__init__.py
sagemaker_ssh_helper/js/drop_studio_file.js
sagemaker_ssh_helper-2.3.0.data/data/sm_ssh/SageMaker_SSH_IDE.ipynb
sagemaker_ssh_helper-2.3.0.dist-info/LICENSE
sagemaker_ssh_helper-2.3.0.dist-info/METADATA
sagemaker_ssh_helper-2.3.0.dist-info/WHEEL
sagemaker_ssh_helper-2.3.0.dist-info/entry_points.txt
sagemaker_ssh_helper-2.3.0.dist-info/top_level.txt
sagemaker_ssh_helper-2.3.0.dist-info/RECORD
