Metadata-Version: 2.1
Name: sagemaker-ssh-helper
Version: 2.3.0
Summary: A helper library to connect into Amazon SageMaker with AWS Systems Manager and SSH (Secure Shell)
Home-page: https://github.com/aws-samples/sagemaker-ssh-helper
Author: Amazon Web Services
Classifier: Development Status :: 4 - Beta
Classifier: Intended Audience :: Developers
Classifier: Natural Language :: English
Classifier: License :: OSI Approved :: MIT No Attribution License (MIT-0)
Classifier: Programming Language :: Python
Classifier: Programming Language :: Python :: 3
Classifier: Programming Language :: Python :: 3.8
Classifier: Programming Language :: Python :: 3.9
Classifier: Programming Language :: Python :: 3.10
Classifier: Programming Language :: Python :: 3.11
Requires-Python: >=3.8
License-File: LICENSE
Requires-Dist: sagemaker >=2.145.0
Requires-Dist: boto3 >=1.34.153
Requires-Dist: botocore >=1.34.153
Requires-Dist: psutil
Provides-Extra: cdk
Requires-Dist: aws-cdk-lib ; extra == 'cdk'
Provides-Extra: dev
Requires-Dist: sagemaker-pytorch-training ; extra == 'dev'
Requires-Dist: sagemaker-pytorch-inference ; extra == 'dev'
Requires-Dist: torch-model-archiver ; extra == 'dev'
Requires-Dist: tox ; extra == 'dev'
Requires-Dist: wheel ; extra == 'dev'
Requires-Dist: build ; extra == 'dev'
Requires-Dist: twine ; extra == 'dev'
Requires-Dist: pydevd-pycharm ~=222.4459.20 ; extra == 'dev'
Requires-Dist: scikit-learn ; extra == 'dev'
Requires-Dist: transformers ; extra == 'dev'
Requires-Dist: py-cpuinfo ; extra == 'dev'
Requires-Dist: deepspeed ; extra == 'dev'
Provides-Extra: dev-macos
Requires-Dist: tensorflow-macos ==2.9.2 ; extra == 'dev-macos'
Requires-Dist: numpy ==1.22.4 ; extra == 'dev-macos'
Provides-Extra: test
Requires-Dist: build ; extra == 'test'
Requires-Dist: coverage ; extra == 'test'
Requires-Dist: flake8 ; extra == 'test'
Requires-Dist: mock ; extra == 'test'
Requires-Dist: pydocstyle ; extra == 'test'
Requires-Dist: pytest ; extra == 'test'
Requires-Dist: pytest-cov ; extra == 'test'
Requires-Dist: pytest-html ; extra == 'test'
Requires-Dist: pytest-profiling ; extra == 'test'
Requires-Dist: pytest-monitor ; extra == 'test'
Requires-Dist: bandit ; extra == 'test'
Requires-Dist: aws-cdk-lib ; extra == 'test'
Requires-Dist: sagemaker-studio-image-build ; extra == 'test'
Requires-Dist: sagemaker-training ; extra == 'test'
Requires-Dist: selenium ; extra == 'test'
Requires-Dist: accelerate[sagemaker] <0.29 ; extra == 'test'
